LICENSE
README.md
okhash.py
setup.py
okhash.egg-info/PKG-INFO
okhash.egg-info/SOURCES.txt
okhash.egg-info/dependency_links.txt
okhash.egg-info/entry_points.txt
okhash.egg-info/top_level.txt