Metadata-Version: 2.1
Name: okhash
Version: 1.0
Summary: Library and CLI for computing O(K)Hash checksums.
Home-page: https://github.com/xaled/okhash
Author: Khalid Grandi
Author-email: kh.grandi@gmail.com
License: MIT
Keywords: library cli hash
Classifier: License :: OSI Approved :: MIT License
Classifier: Operating System :: OS Independent
Classifier: Programming Language :: Python
Requires-Python: >=3
License-File: LICENSE
